genie_flow_invoker/invoker/azure_ai_search.py
genie_flow_invoker_azure_ai_search-0.7.0a1.dist-info/licenses/NOTICES
genie_flow_invoker_azure_ai_search-0.7.0a1.dist-info/METADATA
genie_flow_invoker_azure_ai_search-0.7.0a1.dist-info/WHEEL
genie_flow_invoker_azure_ai_search-0.7.0a1.dist-info/top_level.txt
genie_flow_invoker_azure_ai_search-0.7.0a1.dist-info/RECORD
